spacy_lookups_data/__init__.py
spacy_lookups_data/about.py
spacy_lookups_data/data/bn_lemma_rules.json.gz
spacy_lookups_data/data/bn_source.txt
spacy_lookups_data/data/ca_lemma_exc.json.gz
spacy_lookups_data/data/ca_lemma_index.json.gz
spacy_lookups_data/data/ca_lemma_lookup.json.gz
spacy_lookups_data/data/ca_lemma_rules.json.gz
spacy_lookups_data/data/ca_license.txt
spacy_lookups_data/data/cs_lemma_lookup.json.gz
spacy_lookups_data/data/cs_lexeme_norm.json.gz
spacy_lookups_data/data/da_lemma_lookup.json.gz
spacy_lookups_data/data/da_lexeme_norm.json.gz
spacy_lookups_data/data/de_lemma_lookup.json.gz
spacy_lookups_data/data/de_lexeme_cluster.json.gz
spacy_lookups_data/data/de_lexeme_norm.json.gz
spacy_lookups_data/data/de_lexeme_prob.json.gz
spacy_lookups_data/data/de_lexeme_settings.json.gz
spacy_lookups_data/data/de_orth_variants.json.gz
spacy_lookups_data/data/el_lemma_exc.json.gz
spacy_lookups_data/data/el_lemma_index.json.gz
spacy_lookups_data/data/el_lemma_rules.json.gz
spacy_lookups_data/data/el_lexeme_norm.json.gz
spacy_lookups_data/data/el_lexeme_prob.json.gz
spacy_lookups_data/data/el_lexeme_settings.json.gz
spacy_lookups_data/data/en_lemma_exc.json.gz
spacy_lookups_data/data/en_lemma_index.json.gz
spacy_lookups_data/data/en_lemma_lookup.json.gz
spacy_lookups_data/data/en_lemma_rules.json.gz
spacy_lookups_data/data/en_lexeme_cluster.json.gz
spacy_lookups_data/data/en_lexeme_norm.json.gz
spacy_lookups_data/data/en_lexeme_prob.json.gz
spacy_lookups_data/data/en_lexeme_settings.json.gz
spacy_lookups_data/data/en_license.txt
spacy_lookups_data/data/en_orth_variants.json.gz
spacy_lookups_data/data/es_lemma_exc.json.gz
spacy_lookups_data/data/es_lemma_index.json.gz
spacy_lookups_data/data/es_lemma_lookup.json.gz
spacy_lookups_data/data/es_lemma_rules.json.gz
spacy_lookups_data/data/es_lemma_rules_groups.json.gz
spacy_lookups_data/data/es_lexeme_cluster.json.gz
spacy_lookups_data/data/es_lexeme_prob.json.gz
spacy_lookups_data/data/es_lexeme_settings.json.gz
spacy_lookups_data_la-1.0.5.dist-info/LICENSE
spacy_lookups_data_la-1.0.5.dist-info/METADATA
spacy_lookups_data_la-1.0.5.dist-info/WHEEL
spacy_lookups_data_la-1.0.5.dist-info/entry_points.txt
spacy_lookups_data_la-1.0.5.dist-info/top_level.txt
spacy_lookups_data_la-1.0.5.dist-info/zip-safe
spacy_lookups_data_la-1.0.5.dist-info/RECORD
